Metadata-Version: 2.4
Name: aa-ma-securegroups
Version: 1.6.1
Summary: Member Audit Secure Groups integration for Alliance Auth
Project-URL: Changelog, https://github.com/ppfeufer/aa-ma-securegroups/blob/master/CHANGELOG.md
Project-URL: Codecov, https://codecov.io/gh/ppfeufer/aa-ma-securegroups
Project-URL: Discord, https://discord.gg/fjnHAmk
Project-URL: Documentation, https://github.com/ppfeufer/aa-ma-securegroups/blob/master/README.md
Project-URL: Donation, https://ko-fi.com/ppfeufer
Project-URL: GitHub, https://github.com/ppfeufer/aa-ma-securegroups
Project-URL: Tracker, https://github.com/ppfeufer/aa-ma-securegroups/issues
Project-URL: Translation, https://weblate.ppfeufer.de/projects/alliance-auth-apps/aa-member-audit-secure-groups/
Author-email: Peter Pfeufer <develop@ppfeufer.de>, Erik Kalkoken <kalkoken87@gmail.com>, Rebecca Murphy <rebecca@rcmurphy.me>
Maintainer-email: Peter Pfeufer <develop@ppfeufer.de>
License:                     GNU GENERAL PUBLIC LICENSE
License-File: LICENSE
Keywords: allianceauth,memberaudit,securegroups
Classifier: Environment :: Web Environment
Classifier: Framework :: Django
Classifier: Framework :: Django :: 4.2
Classifier: Intended Audience :: Developers
Classifier: License :: OSI Approved :: GNU General Public License v3 (GPLv3)
Classifier: Operating System :: OS Independent
Classifier: Programming Language :: Python
Classifier: Programming Language :: Python :: 3 :: Only
Classifier: Programming Language :: Python :: 3.10
Classifier: Programming Language :: Python :: 3.11
Classifier: Programming Language :: Python :: 3.12
Classifier: Programming Language :: Python :: 3.13
Classifier: Topic :: Internet :: WWW/HTTP
Classifier: Topic :: Internet :: WWW/HTTP :: Dynamic Content
Requires-Python: <3.14,>=3.10
Requires-Dist: aa-memberaudit>=3.10
Requires-Dist: allianceauth-securegroups>=0.5.1
Requires-Dist: allianceauth<5,>=4.3.1
Provides-Extra: tests-allianceauth-latest
Requires-Dist: coverage; extra == 'tests-allianceauth-latest'
Requires-Dist: django-webtest; extra == 'tests-allianceauth-latest'
